matrixmodule/__init__.py
matrixmodule-0.1.4.dist-info/METADATA
matrixmodule-0.1.4.dist-info/WHEEL
matrixmodule-0.1.4.dist-info/top_level.txt
matrixmodule-0.1.4.dist-info/RECORD
