Metadata-Version: 2.1
Name: matrixmodule
Version: 0.1.4
Summary: A package for matrix operations.
Home-page: https://pypi.org/manage/project/matrixmodule/release/0.0.12/
Author: Elliott Walker
Author-email: <22walkerelliott@gmail.com>
License: UNKNOWN
Keywords: python,linear algebra,matrices,statistics,regression
Platform: UNKNOWN
Classifier: Development Status :: 3 - Alpha
Classifier: Intended Audience :: Education
Classifier: Programming Language :: Python :: 2
Classifier: Programming Language :: Python :: 3
Classifier: Operating System :: MacOS :: MacOS X
Classifier: Operating System :: Microsoft :: Windows
